Workbook

Sheet Read Me
A1: NORTHSTAR CLOUD / READ ME
A3: STARTER FILE | Yellow cells are deliberately unfinished. Do not restyle the model.
A5: USD, unless stated otherwise | B5: Oct-25 | C5: Nov-25 | D5: Dec-25 | E5: Jan-26 | F5: Feb-26 | G5: Mar-26 | H5: Apr-26 | I5: May-26 | J5: Jun-26 | K5: Jul-26 | L5: Aug-26 | M5: Sep-26 | N5: Oct-26 | O5: Nov-26 | P5: Dec-26 | Q5: FY26 / Exit | S5: MODEL NOTES
A7: Forecast completion exercise / controlled change of direction
A10: Complete the current finance request provided in the Harbor instruction. This engagement may include later follow-ups. Do not anticipate unissued changes. Keep task-owned formulas editable and preserve the supplied presentation.
A14: COLOR KEY: pale blue = historical actuals; green = fixed source assumptions; yellow with blue text = driver inputs; yellow with dark text = formula completion areas; gray = existing formulas (preserve). Blank yellow cells are intentional, not missing data.
A18: MODEL FLOW: Assumptions -> Drivers -> Revenue / Cohorts -> P&L -> Working Capital -> Cash Flow -> Checks. Historical holds Oct-Dec 2025 actuals. The active instruction determines which forecast method and completion areas apply.
A22: PRESERVE: sheet names/order; row/column positions; number formats; fonts/fills/borders; merged cells; dimensions; freeze panes; validations; comments; print settings; chart; conditional formatting and pre-existing formulas. Only write designated yellow cells.
A26: Data is entirely synthetic. Monthly customer counts are expected values and may be fractional. Do not round intermediate calculations. Existing formulas show blanks until their source schedules are complete. FY26 / Exit is a full-year sum for flows and December for balances, rates and counts.
A30: Save /app/output/Northstar_Forecast_Completed.xlsx and /app/output/handoff.json. Cached formula results are optional; a disposable copy is recalculated by the verifier. Only the active instruction and any subsequently issued revision determine acceptance.

Sheet Assumptions
A1: NORTHSTAR CLOUD / ASSUMPTIONS
A3: FIXED SOURCE DATA | Copy the forecast assumptions into Drivers; do not change this sheet.
A5: USD, unless stated otherwise | B5: Oct-25 | C5: Nov-25 | D5: Dec-25 | E5: Jan-26 | F5: Feb-26 | G5: Mar-26 | H5: Apr-26 | I5: May-26 | J5: Jun-26 | K5: Jul-26 | L5: Aug-26 | M5: Sep-26 | N5: Oct-26 | O5: Nov-26 | P5: Dec-26 | Q5: FY26 / Exit | S5: MODEL NOTES
A6: Legacy monthly revenue growth | E6: 0.025 | F6: 0.025 | G6: 0.03 | H6: 0.03 | I6: 0.035 | J6: 0.035 | K6: 0.03 | L6: 0.03 | M6: 0.025 | N6: 0.025 | O6: 0.02 | P6: 0.02 | Q6: 0.02
A7: Hosting cost / revenue | E7: 0.2 | F7: 0.2 | G7: 0.2 | H7: 0.2 | I7: 0.2 | J7: 0.2 | K7: 0.2 | L7: 0.2 | M7: 0.2 | N7: 0.2 | O7: 0.2 | P7: 0.2 | Q7: 0.2
A8: Cash tax rate | E8: 0.25 | F8: 0.25 | G8: 0.25 | H8: 0.25 | I8: 0.25 | J8: 0.25 | K8: 0.25 | L8: 0.25 | M8: 0.25 | N8: 0.25 | O8: 0.25 | P8: 0.25 | Q8: 0.25
A9: New customer additions | E9: 40 | F9: 42 | G9: 44 | H9: 46 | I9: 48 | J9: 50 | K9: 52 | L9: 54 | M9: 56 | N9: 58 | O9: 60 | P9: 62 | Q9: 62
A10: Existing-customer monthly churn | E10: 0.02 | F10: 0.02 | G10: 0.02 | H10: 0.02 | I10: 0.02 | J10: 0.02 | K10: 0.02 | L10: 0.02 | M10: 0.02 | N10: 0.02 | O10: 0.02 | P10: 0.02 | Q10: 0.02
A11: New-cohort monthly churn | E11: 0.015 | F11: 0.015 | G11: 0.015 | H11: 0.015 | I11: 0.015 | J11: 0.015 | K11: 0.015 | L11: 0.015 | M11: 0.015 | N11: 0.015 | O11: 0.015 | P11: 0.015 | Q11: 0.015
A12: Opening existing customers | E12: 1000 | F12: 1000 | G12: 1000 | H12: 1000 | I12: 1000 | J12: 1000 | K12: 1000 | L12: 1000 | M12: 1000 | N12: 1000 | O12: 1000 | P12: 1000 | Q12: 1000
A13: Existing starting monthly ARPC | E13: 120 | F13: 120 | G13: 120 | H13: 120 | I13: 120 | J13: 120 | K13: 120 | L13: 120 | M13: 120 | N13: 120 | O13: 120 | P13: 120 | Q13: 120
A14: New-cohort starting monthly ARPC | E14: 135 | F14: 135 | G14: 135 | H14: 135 | I14: 135 | J14: 135 | K14: 135 | L14: 135 | M14: 135 | N14: 135 | O14: 135 | P14: 135 | Q14: 135
A15: Calendar-month price uplift | E15: 0 | F15: 0 | G15: 0 | H15: 0 | I15: 0 | J15: 0 | K15: 0.04 | L15: 0 | M15: 0 | N15: 0 | O15: 0 | P15: 0 | Q15: 0
A16: DSO / actual days in month | E16: 35 | F16: 35 | G16: 35 | H16: 35 | I16: 35 | J16: 35 | K16: 35 | L16: 35 | M16: 35 | N16: 35 | O16: 35 | P16: 35 | Q16: 35
A17: DPO / actual days in month | E17: 25 | F17: 25 | G17: 25 | H17: 25 | I17: 25 | J17: 25 | K17: 25 | L17: 25 | M17: 25 | N17: 25 | O17: 25 | P17: 25 | Q17: 25
... A25: Days in month | E25: 31 | F25: 28 | G25: 31 | H25: 30 | I25: 31 | J25: 30 | K25: 31 | L25: 31 | M25: 30 | N25: 31 | O25: 30 | P25: 31 | Q25: 31
S27: Rows 12-14 are reference constants. Existing opening customers and ARPC initialize January only; new cohorts use their launch-month ARPC.
S29: The July uplift applies to every cohort alive in July, including the July launch cohort. Later launch cohorts do not inherit earlier uplifts.

Sheet Drivers
A1: NORTHSTAR CLOUD / DRIVERS
A3: A | Complete yellow driver inputs from the fixed Assumptions sheet.
A5: USD, unless stated otherwise | B5: Oct-25 | C5: Nov-25 | D5: Dec-25 | E5: Jan-26 | F5: Feb-26 | G5: Mar-26 | H5: Apr-26 | I5: May-26 | J5: Jun-26 | K5: Jul-26 | L5: Aug-26 | M5: Sep-26 | N5: Oct-26 | O5: Nov-26 | P5: Dec-26 | Q5: FY26 / Exit | S5: MODEL NOTES
A6: Legacy monthly revenue growth | E6: =Assumptions!E6 | F6: =Assumptions!F6 | G6: =Assumptions!G6 | H6: =Assumptions!H6 | I6: =Assumptions!I6 | J6: =Assumptions!J6 | K6: =Assumptions!K6 | L6: =Assumptions!L6 | ... P6: =Assumptions!P6 | Q6: =IF(COUNT(E6:P6)=12,P6,"")
A7: Hosting cost / revenue | E7: =Assumptions!E7 | F7: =Assumptions!F7 | G7: =Assumptions!G7 | H7: =Assumptions!H7 | I7: =Assumptions!I7 | J7: =Assumptions!J7 | K7: =Assumptions!K7 | L7: =Assumptions!L7 | ... P7: =Assumptions!P7 | Q7: =IF(COUNT(E7:P7)=12,P7,"")
A8: Cash tax rate | E8: =Assumptions!E8 | F8: =Assumptions!F8 | G8: =Assumptions!G8 | H8: =Assumptions!H8 | I8: =Assumptions!I8 | J8: =Assumptions!J8 | K8: =Assumptions!K8 | L8: =Assumptions!L8 | ... P8: =Assumptions!P8 | Q8: =IF(COUNT(E8:P8)=12,P8,"")
A9: New customer additions | E9: =Assumptions!E9 | F9: =Assumptions!F9 | G9: =Assumptions!G9 | H9: =Assumptions!H9 | I9: =Assumptions!I9 | J9: =Assumptions!J9 | K9: =Assumptions!K9 | L9: =Assumptions!L9 | ... P9: =Assumptions!P9 | Q9: =IF(COUNT(E9:P9)=12,P9,"")
A10: Existing-customer monthly churn | E10: =Assumptions!E10 | F10: =Assumptions!F10 | G10: =Assumptions!G10 | H10: =Assumptions!H10 | I10: =Assumptions!I10 | J10: =Assumptions!J10 | K10: =Assumptions!K10 | L10: =Assumptions!L10 | ... P10: =Assumptions!P10 | Q10: =IF(COUNT(E10:P10)=12,P10,"")
A11: New-cohort monthly churn | E11: =Assumptions!E11 | F11: =Assumptions!F11 | G11: =Assumptions!G11 | H11: =Assumptions!H11 | I11: =Assumptions!I11 | J11: =Assumptions!J11 | K11: =Assumptions!K11 | L11: =Assumptions!L11 | ... P11: =Assumptions!P11 | Q11: =IF(COUNT(E11:P11)=12,P11,"")
A12: Opening existing customers | E12: =Assumptions!E12 | F12: =Assumptions!F12 | G12: =Assumptions!G12 | H12: =Assumptions!H12 | I12: =Assumptions!I12 | J12: =Assumptions!J12 | K12: =Assumptions!K12 | L12: =Assumptions!L12 | ... P12: =Assumptions!P12 | Q12: =IF(COUNT(E12:P12)=12,P12,"")
A13: Existing starting monthly ARPC | E13: =Assumptions!E13 | F13: =Assumptions!F13 | G13: =Assumptions!G13 | H13: =Assumptions!H13 | I13: =Assumptions!I13 | J13: =Assumptions!J13 | K13: =Assumptions!K13 | L13: =Assumptions!L13 | ... P13: =Assumptions!P13 | Q13: =IF(COUNT(E13:P13)=12,P13,"")
A14: New-cohort starting monthly ARPC | E14: =Assumptions!E14 | F14: =Assumptions!F14 | G14: =Assumptions!G14 | H14: =Assumptions!H14 | I14: =Assumptions!I14 | J14: =Assumptions!J14 | K14: =Assumptions!K14 | L14: =Assumptions!L14 | ... P14: =Assumptions!P14 | Q14: =IF(COUNT(E14:P14)=12,P14,"")
A15: Calendar-month price uplift | E15: =Assumptions!E15 | F15: =Assumptions!F15 | G15: =Assumptions!G15 | H15: =Assumptions!H15 | I15: =Assumptions!I15 | J15: =Assumptions!J15 | K15: =Assumptions!K15 | L15: =Assumptions!L15 | ... P15: =Assumptions!P15 | Q15: =IF(COUNT(E15:P15)=12,P15,"")
A16: DSO / actual days in month | E16: =Assumptions!E16 | F16: =Assumptions!F16 | G16: =Assumptions!G16 | H16: =Assumptions!H16 | I16: =Assumptions!I16 | J16: =Assumptions!J16 | K16: =Assumptions!K16 | L16: =Assumptions!L16 | ... P16: =Assumptions!P16 | Q16: =IF(COUNT(E16:P16)=12,P16,"")
A17: DPO / actual days in month | E17: =Assumptions!E17 | F17: =Assumptions!F17 | G17: =Assumptions!G17 | H17: =Assumptions!H17 | I17: =Assumptions!I17 | J17: =Assumptions!J17 | K17: =Assumptions!K17 | L17: =Assumptions!L17 | ... P17: =Assumptions!P17 | Q17: =IF(COUNT(E17:P17)=12,P17,"")
... A25: Days in month | E25: =Assumptions!E25 | F25: =Assumptions!F25 | G25: =Assumptions!G25 | H25: =Assumptions!H25 | I25: =Assumptions!I25 | J25: =Assumptions!J25 | K25: =Assumptions!K25 | L25: =Assumptions!L25 | ... P25: =Assumptions!P25 | Q25: =IF(COUNT(E25:P25)=12,P25,"")
S27: Row 6 is the initial method only. After the follow-up, retain it for audit but do not use it in any forecast revenue or cash-flow dependency.

Sheet Historical
A1: NORTHSTAR CLOUD / HISTORICAL
A3: IMMUTABLE ACTUALS | Three months ending December 2025. Forecast cells on this sheet are unused.
A5: USD, unless stated otherwise | B5: Oct-25 | C5: Nov-25 | D5: Dec-25 | E5: Jan-26 | F5: Feb-26 | G5: Mar-26 | H5: Apr-26 | I5: May-26 | J5: Jun-26 | K5: Jul-26 | L5: Aug-26 | M5: Sep-26 | N5: Oct-26 | O5: Nov-26 | P5: Dec-26 | Q5: FY26 / Exit | S5: MODEL NOTES
A6: Subscription revenue | B6: 115000 | C6: 118000 | D6: 120000
A7: Hosting cost | B7: 23000 | C7: 23600 | D7: 24000
A8: Gross profit | B8: 92000 | C8: 94400 | D8: 96000
A9: Payroll | B9: 41500 | C9: 41750 | D9: 42000
A10: Sales & marketing | B10: 17250 | C10: 17700 | D10: 18000
A11: General & administrative | B11: 9940 | C11: 9970 | D11: 10000
A12: EBITDA | B12: 23310 | C12: 24980 | D12: 26000
A13: Depreciation | B13: 2500 | C13: 2500 | D13: 2500
A14: EBIT | B14: 20810 | C14: 22480 | D14: 23500
A15: Interest | B15: 250 | C15: 250 | D15: 250
A16: Cash taxes | B16: 5140 | C16: 5557.5 | D16: 5812.5
A17: Net income | B17: 15420 | C17: 16672.5 | D17: 17437.5
... A25: Exit monthly ARPC | B25: 119.79167 | C25: 120.40816 | D25: 120
S27: December balances seed January. Cash taxes are based on positive earnings before tax; losses generate no refunds or tax-loss carryforward in this exercise.

Sheet Cohorts
A1: NORTHSTAR CLOUD / COHORTS
A3: B replacement only | Expected active customers and monthly recurring revenue by acquisition cohort.
A5: USD, unless stated otherwise | B5: Oct-25 | C5: Nov-25 | D5: Dec-25 | E5: Jan-26 | F5: Feb-26 | G5: Mar-26 | H5: Apr-26 | I5: May-26 | J5: Jun-26 | K5: Jul-26 | L5: Aug-26 | M5: Sep-26 | N5: Oct-26 | O5: Nov-26 | P5: Dec-26 | Q5: FY26 / Exit | S5: MODEL NOTES
A6: EXPECTED ACTIVE CUSTOMERS
A8: Existing base at 31-Dec-2025 | E8: =Drivers!E12*(1-Drivers!E10) | F8: =E8*(1-Drivers!F10) | G8: =F8*(1-Drivers!G10) | H8: =G8*(1-Drivers!H10) | I8: =H8*(1-Drivers!I10) | J8: =I8*(1-Drivers!J10) | K8: =J8*(1-Drivers!K10) | L8: =K8*(1-Drivers!L10) | M8: =L8*(1-Drivers!M10) | ... P8: =O8*(1-Drivers!P10) | Q8: =IF(COUNT(E8:P8)=12,P8,"") | S8: Existing base: churn starts in January. January expected customers = opening base x (1 - existing churn). Later months roll forward.
A9: Jan-2026 acquisition cohort | E9: =Drivers!E9 | F9: =E9*(1-Drivers!F11) | G9: =F9*(1-Drivers!G11) | H9: =G9*(1-Drivers!H11) | I9: =H9*(1-Drivers!I11) | J9: =I9*(1-Drivers!J11) | K9: =J9*(1-Drivers!K11) | L9: =K9*(1-Drivers!L11) | M9: =L9*(1-Drivers!M11) | ... P9: =O9*(1-Drivers!P11) | Q9: =IF(COUNT(E9:P9)=12,P9,"")
A10: Feb-2026 acquisition cohort | E10: =0 | F10: =Drivers!F9 | G10: =F10*(1-Drivers!G11) | H10: =G10*(1-Drivers!H11) | I10: =H10*(1-Drivers!I11) | J10: =I10*(1-Drivers!J11) | K10: =J10*(1-Drivers!K11) | L10: =K10*(1-Drivers!L11) | M10: =L10*(1-Drivers!M11) | N10: =M10*(1-Drivers!N11) | ... P10: =O10*(1-Drivers!P11) | Q10: =IF(COUNT(E10:P10)=12,P10,"")
A11: Mar-2026 acquisition cohort | E11: =0 | F11: =0 | G11: =Drivers!G9 | H11: =G11*(1-Drivers!H11) | I11: =H11*(1-Drivers!I11) | J11: =I11*(1-Drivers!J11) | K11: =J11*(1-Drivers!K11) | L11: =K11*(1-Drivers!L11) | M11: =L11*(1-Drivers!M11) | N11: =M11*(1-Drivers!N11) | O11: =N11*(1-Drivers!O11) | P11: =O11*(1-Drivers!P11) | Q11: =IF(COUNT(E11:P11)=12,P11,"")
A12: Apr-2026 acquisition cohort | E12: =0 | F12: =0 | G12: =0 | H12: =Drivers!H9 | I12: =H12*(1-Drivers!I11) | J12: =I12*(1-Drivers!J11) | K12: =J12*(1-Drivers!K11) | L12: =K12*(1-Drivers!L11) | M12: =L12*(1-Drivers!M11) | N12: =M12*(1-Drivers!N11) | O12: =N12*(1-Drivers!O11) | P12: =O12*(1-Drivers!P11) | Q12: =IF(COUNT(E12:P12)=12,P12,"") | S12: New cohort: zero before launch; launch customers = that month's additions (no launch-month churn). Apply new-cohort churn in each later month.
A13: May-2026 acquisition cohort | E13: =0 | F13: =0 | G13: =0 | H13: =0 | I13: =Drivers!I9 | J13: =I13*(1-Drivers!J11) | K13: =J13*(1-Drivers!K11) | L13: =K13*(1-Drivers!L11) | M13: =L13*(1-Drivers!M11) | N13: =M13*(1-Drivers!N11) | O13: =N13*(1-Drivers!O11) | P13: =O13*(1-Drivers!P11) | Q13: =IF(COUNT(E13:P13)=12,P13,"")
A14: Jun-2026 acquisition cohort | E14: =0 | F14: =0 | G14: =0 | H14: =0 | I14: =0 | J14: =Drivers!J9 | K14: =J14*(1-Drivers!K11) | L14: =K14*(1-Drivers!L11) | M14: =L14*(1-Drivers!M11) | N14: =M14*(1-Drivers!N11) | O14: =N14*(1-Drivers!O11) | P14: =O14*(1-Drivers!P11) | Q14: =IF(COUNT(E14:P14)=12,P14,"")
A15: Jul-2026 acquisition cohort | E15: =0 | F15: =0 | G15: =0 | H15: =0 | I15: =0 | J15: =0 | K15: =Drivers!K9 | L15: =K15*(1-Drivers!L11) | M15: =L15*(1-Drivers!M11) | N15: =M15*(1-Drivers!N11) | O15: =N15*(1-Drivers!O11) | P15: =O15*(1-Drivers!P11) | Q15: =IF(COUNT(E15:P15)=12,P15,"")
A16: Aug-2026 acquisition cohort | E16: =0 | F16: =0 | G16: =0 | H16: =0 | I16: =0 | J16: =0 | K16: =0 | L16: =Drivers!L9 | M16: =L16*(1-Drivers!M11) | N16: =M16*(1-Drivers!N11) | O16: =N16*(1-Drivers!O11) | P16: =O16*(1-Drivers!P11) | Q16: =IF(COUNT(E16:P16)=12,P16,"")
A17: Sep-2026 acquisition cohort | E17: =0 | F17: =0 | G17: =0 | H17: =0 | I17: =0 | J17: =0 | K17: =0 | L17: =0 | M17: =Drivers!M9 | N17: =M17*(1-Drivers!N11) | O17: =N17*(1-Drivers!O11) | P17: =O17*(1-Drivers!P11) | Q17: =IF(COUNT(E17:P17)=12,P17,"") | S17: Keep fractions. Use explicit =0 formulas in pre-launch cells so the total-row completion guards can count all 13 cohorts.
A18: Oct-2026 acquisition cohort | E18: =0 | F18: =0 | G18: =0 | H18: =0 | I18: =0 | J18: =0 | K18: =0 | L18: =0 | M18: =0 | N18: =Drivers!N9 | O18: =N18*(1-Drivers!O11) | P18: =O18*(1-Drivers!P11) | Q18: =IF(COUNT(E18:P18)=12,P18,"")
A19: Nov-2026 acquisition cohort | E19: =0 | F19: =0 | G19: =0 | H19: =0 | I19: =0 | J19: =0 | K19: =0 | L19: =0 | ... N19: =0 | O19: =Drivers!O9 | P19: =O19*(1-Drivers!P11) | Q19: =IF(COUNT(E19:P19)=12,P19,"")
A20: Dec-2026 acquisition cohort | E20: =0 | F20: =0 | G20: =0 | H20: =0 | I20: =0 | J20: =0 | K20: =0 | L20: =0 | ... O20: =0 | P20: =Drivers!P9 | Q20: =IF(COUNT(E20:P20)=12,P20,"")
A21: Total active customers | E21: =IF(COUNT(E8:E20)=13,SUM(E8:E20),"") | F21: =IF(COUNT(F8:F20)=13,SUM(F8:F20),"") | G21: =IF(COUNT(G8:G20)=13,SUM(G8:G20),"") | H21: =IF(COUNT(H8:H20)=13,SUM(H8:H20),"") | I21: =IF(COUNT(I8:I20)=13,SUM(I8:I20),"") | J21: =IF(COUNT(J8:J20)=13,SUM(J8:J20),"") | K21: =IF(COUNT(K8:K20)=13,SUM(K8:K20),"") | L21: =IF(COUNT(L8:L20)=13,SUM(L8:L20),"") | ... P21: =IF(COUNT(P8:P20)=13,SUM(P8:P20),"") | Q21: =IF(COUNT(E21:P21)=12,P21,"")
A23: MONTHLY RECURRING REVENUE
A25: Existing base at 31-Dec-2025 | E25: =E8*Drivers!E13*(1+Drivers!E15) | F25: =F8*Drivers!E13*(1+Drivers!E15) | G25: =G8*Drivers!E13*(1+Drivers!E15) | H25: =H8*Drivers!E13*(1+Drivers!E15)*(1+Drivers!F15)*(1+Drivers!G15)*(1+Drivers!H15) | I25: =I8*Drivers!E13*(1+Drivers!E15)*(1+Drivers!F15)*(1+Drivers!G15)*(1+Drivers!H15) | J25: =J8*Drivers!E13*(1+Drivers!E15)*(1+Drivers!F15)*(1+Drivers!G15)*(1+Drivers!H15) | K25: =K8*Drivers!E13*(1+Drivers!E15)*(1+Drivers!F15)*(1+Drivers!G15)*(1+Drivers!H15)*(1+Drivers!I15)*(1+Drivers!J15)*(1+Drivers!K15) | L25: =L8*Drivers!E13*(1+Drivers!E15)*(1+Drivers!F15)*(1+Drivers!G15)*(1+Drivers!H15)*(1+Drivers!I15)*(1+Drivers!J15)*(1+Drivers!K15) | M25: =M8*Drivers!E13*(1+Drivers!E15)*(1+Drivers!F15)*(1+Drivers!G15)*(1+Drivers!H15)*(1+Drivers!I15)*(1+Drivers!J15)*(1+Drivers!K15) | N25: =N8*Drivers!E13*(1+Drivers!E15)*(1+Drivers!F15)*(1+Drivers!G15)*(1+Drivers!H15)*(1+Drivers!I15)*(1+Drivers!J15)*(1+Drivers!K15)*(1+Drivers!L15)*(1+Drivers!M15)*(1+Drivers!N15) | O25: =O8*Drivers!E13*(1+Drivers!E15)*(1+Drivers!F15)*(1+Drivers!G15)*(1+Drivers!H15)*(1+Drivers!I15)*(1+Drivers!J15)*(1+Drivers!K15)*(1+Drivers!L15)*(1+Drivers!M15)*(1+Drivers!N15) | P25: =P8*Drivers!E13*(1+Drivers!E15)*(1+Drivers!F15)*(1+Drivers!G15)*(1+Drivers!H15)*(1+Drivers!I15)*(1+Drivers!J15)*(1+Drivers!K15)*(1+Drivers!L15)*(1+Drivers!M15)*(1+Drivers!N15) | Q25: =IF(COUNT(E25:P25)=12,SUM(E25:P25),"") | S25: Existing January MRR = active customers x starting ARPC x (1 + January uplift). Later MRR = prior MRR x customer-retention factor x (1 + current uplift).
A26: Jan-2026 acquisition cohort | E26: =E9*Drivers!E14 | F26: =F9*Drivers!E14 | G26: =G9*Drivers!E14 | H26: =H9*Drivers!E14*(1+Drivers!E15)*(1+Drivers!F15)*(1+Drivers!G15)*(1+Drivers!H15) | I26: =I9*Drivers!E14*(1+Drivers!E15)*(1+Drivers!F15)*(1+Drivers!G15)*(1+Drivers!H15) | J26: =J9*Drivers!E14*(1+Drivers!E15)*(1+Drivers!F15)*(1+Drivers!G15)*(1+Drivers!H15) | K26: =K9*Drivers!E14*(1+Drivers!E15)*(1+Drivers!F15)*(1+Drivers!G15)*(1+Drivers!H15)*(1+Drivers!I15)*(1+Drivers!J15)*(1+Drivers!K15) | L26: =L9*Drivers!E14*(1+Drivers!E15)*(1+Drivers!F15)*(1+Drivers!G15)*(1+Drivers!H15)*(1+Drivers!I15)*(1+Drivers!J15)*(1+Drivers!K15) | M26: =M9*Drivers!E14*(1+Drivers!E15)*(1+Drivers!F15)*(1+Drivers!G15)*(1+Drivers!H15)*(1+Drivers!I15)*(1+Drivers!J15)*(1+Drivers!K15) | N26: =N9*Drivers!E14*(1+Drivers!E15)*(1+Drivers!F15)*(1+Drivers!G15)*(1+Drivers!H15)*(1+Drivers!I15)*(1+Drivers!J15)*(1+Drivers!K15)*(1+Drivers!L15)*(1+Drivers!M15)*(1+Drivers!N15) | O26: =O9*Drivers!E14*(1+Drivers!E15)*(1+Drivers!F15)*(1+Drivers!G15)*(1+Drivers!H15)*(1+Drivers!I15)*(1+Drivers!J15)*(1+Drivers!K15)*(1+Drivers!L15)*(1+Drivers!M15)*(1+Drivers!N15) | P26: =P9*Drivers!E14*(1+Drivers!E15)*(1+Drivers!F15)*(1+Drivers!G15)*(1+Drivers!H15)*(1+Drivers!I15)*(1+Drivers!J15)*(1+Drivers!K15)*(1+Drivers!L15)*(1+Drivers!M15)*(1+Drivers!N15) | Q26: =IF(COUNT(E26:P26)=12,SUM(E26:P26),"")
A27: Feb-2026 acquisition cohort | E27: =0 | F27: =F10*Drivers!F14 | G27: =G10*Drivers!F14 | H27: =H10*Drivers!F14 | I27: =I10*Drivers!F14*(1+Drivers!F15)*(1+Drivers!G15)*(1+Drivers!H15)*(1+Drivers!I15) | J27: =J10*Drivers!F14*(1+Drivers!F15)*(1+Drivers!G15)*(1+Drivers!H15)*(1+Drivers!I15) | K27: =K10*Drivers!F14*(1+Drivers!F15)*(1+Drivers!G15)*(1+Drivers!H15)*(1+Drivers!I15) | L27: =L10*Drivers!F14*(1+Drivers!F15)*(1+Drivers!G15)*(1+Drivers!H15)*(1+Drivers!I15)*(1+Drivers!J15)*(1+Drivers!K15)*(1+Drivers!L15) | M27: =M10*Drivers!F14*(1+Drivers!F15)*(1+Drivers!G15)*(1+Drivers!H15)*(1+Drivers!I15)*(1+Drivers!J15)*(1+Drivers!K15)*(1+Drivers!L15) | N27: =N10*Drivers!F14*(1+Drivers!F15)*(1+Drivers!G15)*(1+Drivers!H15)*(1+Drivers!I15)*(1+Drivers!J15)*(1+Drivers!K15)*(1+Drivers!L15) | O27: =O10*Drivers!F14*(1+Drivers!F15)*(1+Drivers!G15)*(1+Drivers!H15)*(1+Drivers!I15)*(1+Drivers!J15)*(1+Drivers!K15)*(1+Drivers!L15)*(1+Drivers!M15)*(1+Drivers!N15)*(1+Drivers!O15) | P27: =P10*Drivers!F14*(1+Drivers!F15)*(1+Drivers!G15)*(1+Drivers!H15)*(1+Drivers!I15)*(1+Drivers!J15)*(1+Drivers!K15)*(1+Drivers!L15)*(1+Drivers!M15)*(1+Drivers!N15)*(1+Drivers!O15) | Q27: =IF(COUNT(E27:P27)=12,SUM(E27:P27),"")
A28: Mar-2026 acquisition cohort | E28: =0 | F28: =0 | G28: =G11*Drivers!G14 | H28: =H11*Drivers!G14 | I28: =I11*Drivers!G14 | J28: =J11*Drivers!G14*(1+Drivers!G15)*(1+Drivers!H15)*(1+Drivers!I15)*(1+Drivers!J15) | K28: =K11*Drivers!G14*(1+Drivers!G15)*(1+Drivers!H15)*(1+Drivers!I15)*(1+Drivers!J15) | L28: =L11*Drivers!G14*(1+Drivers!G15)*(1+Drivers!H15)*(1+Drivers!I15)*(1+Drivers!J15) | M28: =M11*Drivers!G14*(1+Drivers!G15)*(1+Drivers!H15)*(1+Drivers!I15)*(1+Drivers!J15)*(1+Drivers!K15)*(1+Drivers!L15)*(1+Drivers!M15) | N28: =N11*Drivers!G14*(1+Drivers!G15)*(1+Drivers!H15)*(1+Drivers!I15)*(1+Drivers!J15)*(1+Drivers!K15)*(1+Drivers!L15)*(1+Drivers!M15) | O28: =O11*Drivers!G14*(1+Drivers!G15)*(1+Drivers!H15)*(1+Drivers!I15)*(1+Drivers!J15)*(1+Drivers!K15)*(1+Drivers!L15)*(1+Drivers!M15) | P28: =P11*Drivers!G14*(1+Drivers!G15)*(1+Drivers!H15)*(1+Drivers!I15)*(1+Drivers!J15)*(1+Drivers!K15)*(1+Drivers!L15)*(1+Drivers!M15)*(1+Drivers!N15)*(1+Drivers!O15)*(1+Drivers!P15) | Q28: =IF(COUNT(E28:P28)=12,SUM(E28:P28),"")
A29: Apr-2026 acquisition cohort | E29: =0 | F29: =0 | G29: =0 | H29: =H12*Drivers!H14 | I29: =I12*Drivers!H14 | J29: =J12*Drivers!H14 | K29: =K12*Drivers!H14*(1+Drivers!H15)*(1+Drivers!I15)*(1+Drivers!J15)*(1+Drivers!K15) | L29: =L12*Drivers!H14*(1+Drivers!H15)*(1+Drivers!I15)*(1+Drivers!J15)*(1+Drivers!K15) | M29: =M12*Drivers!H14*(1+Drivers!H15)*(1+Drivers!I15)*(1+Drivers!J15)*(1+Drivers!K15) | N29: =N12*Drivers!H14*(1+Drivers!H15)*(1+Drivers!I15)*(1+Drivers!J15)*(1+Drivers!K15)*(1+Drivers!L15)*(1+Drivers!M15)*(1+Drivers!N15) | O29: =O12*Drivers!H14*(1+Drivers!H15)*(1+Drivers!I15)*(1+Drivers!J15)*(1+Drivers!K15)*(1+Drivers!L15)*(1+Drivers!M15)*(1+Drivers!N15) | P29: =P12*Drivers!H14*(1+Drivers!H15)*(1+Drivers!I15)*(1+Drivers!J15)*(1+Drivers!K15)*(1+Drivers!L15)*(1+Drivers!M15)*(1+Drivers!N15) | Q29: =IF(COUNT(E29:P29)=12,SUM(E29:P29),"")
A30: May-2026 acquisition cohort | E30: =0 | F30: =0 | G30: =0 | H30: =0 | I30: =I13*Drivers!I14 | J30: =J13*Drivers!I14 | K30: =K13*Drivers!I14 | L30: =L13*Drivers!I14*(1+Drivers!I15)*(1+Drivers!J15)*(1+Drivers!K15)*(1+Drivers!L15) | M30: =M13*Drivers!I14*(1+Drivers!I15)*(1+Drivers!J15)*(1+Drivers!K15)*(1+Drivers!L15) | N30: =N13*Drivers!I14*(1+Drivers!I15)*(1+Drivers!J15)*(1+Drivers!K15)*(1+Drivers!L15) | O30: =O13*Drivers!I14*(1+Drivers!I15)*(1+Drivers!J15)*(1+Drivers!K15)*(1+Drivers!L15)*(1+Drivers!M15)*(1+Drivers!N15)*(1+Drivers!O15) | P30: =P13*Drivers!I14*(1+Drivers!I15)*(1+Drivers!J15)*(1+Drivers!K15)*(1+Drivers!L15)*(1+Drivers!M15)*(1+Drivers!N15)*(1+Drivers!O15) | Q30: =IF(COUNT(E30:P30)=12,SUM(E30:P30),"") | S30: New launch-month MRR = launch customers x launch-month starting ARPC x (1 + launch-month uplift). Later months roll prior MRR with new-cohort churn and the current uplift.
A31: Jun-2026 acquisition cohort | E31: =0 | F31: =0 | G31: =0 | H31: =0 | I31: =0 | J31: =J14*Drivers!J14 | K31: =K14*Drivers!J14 | L31: =L14*Drivers!J14 | M31: =M14*Drivers!J14*(1+Drivers!J15)*(1+Drivers!K15)*(1+Drivers!L15)*(1+Drivers!M15) | N31: =N14*Drivers!J14*(1+Drivers!J15)*(1+Drivers!K15)*(1+Drivers!L15)*(1+Drivers!M15) | O31: =O14*Drivers!J14*(1+Drivers!J15)*(1+Drivers!K15)*(1+Drivers!L15)*(1+Drivers!M15) | P31: =P14*Drivers!J14*(1+Drivers!J15)*(1+Drivers!K15)*(1+Drivers!L15)*(1+Drivers!M15)*(1+Drivers!N15)*(1+Drivers!O15)*(1+Drivers!P15) | Q31: =IF(COUNT(E31:P31)=12,SUM(E31:P31),"")
A32: Jul-2026 acquisition cohort | E32: =0 | F32: =0 | G32: =0 | H32: =0 | I32: =0 | J32: =0 | K32: =K15*Drivers!K14 | L32: =L15*Drivers!K14 | M32: =M15*Drivers!K14 | N32: =N15*Drivers!K14*(1+Drivers!K15)*(1+Drivers!L15)*(1+Drivers!M15)*(1+Drivers!N15) | O32: =O15*Drivers!K14*(1+Drivers!K15)*(1+Drivers!L15)*(1+Drivers!M15)*(1+Drivers!N15) | P32: =P15*Drivers!K14*(1+Drivers!K15)*(1+Drivers!L15)*(1+Drivers!M15)*(1+Drivers!N15) | Q32: =IF(COUNT(E32:P32)=12,SUM(E32:P32),"")
A33: Aug-2026 acquisition cohort | E33: =0 | F33: =0 | G33: =0 | H33: =0 | I33: =0 | J33: =0 | K33: =0 | L33: =L16*Drivers!L14 | M33: =M16*Drivers!L14 | N33: =N16*Drivers!L14 | O33: =O16*Drivers!L14*(1+Drivers!L15)*(1+Drivers!M15)*(1+Drivers!N15)*(1+Drivers!O15) | P33: =P16*Drivers!L14*(1+Drivers!L15)*(1+Drivers!M15)*(1+Drivers!N15)*(1+Drivers!O15) | Q33: =IF(COUNT(E33:P33)=12,SUM(E33:P33),"")
A34: Sep-2026 acquisition cohort | E34: =0 | F34: =0 | G34: =0 | H34: =0 | I34: =0 | J34: =0 | K34: =0 | L34: =0 | M34: =M17*Drivers!M14 | N34: =N17*Drivers!M14 | O34: =O17*Drivers!M14 | P34: =P17*Drivers!M14*(1+Drivers!M15)*(1+Drivers!N15)*(1+Drivers!O15)*(1+Drivers!P15) | Q34: =IF(COUNT(E34:P34)=12,SUM(E34:P34),"")
A35: Oct-2026 acquisition cohort | E35: =0 | F35: =0 | G35: =0 | H35: =0 | I35: =0 | J35: =0 | K35: =0 | L35: =0 | M35: =0 | N35: =N18*Drivers!N14 | O35: =O18*Drivers!N14 | P35: =P18*Drivers!N14 | Q35: =IF(COUNT(E35:P35)=12,SUM(E35:P35),"") | S35: Revenue equals MRR: full-month billing for all active expected customers; no services, bookings, annual prepayments, discounts or deferred revenue.
A36: Nov-2026 acquisition cohort | E36: =0 | F36: =0 | G36: =0 | H36: =0 | I36: =0 | J36: =0 | K36: =0 | L36: =0 | ... N36: =0 | O36: =O19*Drivers!O14 | P36: =P19*Drivers!O14 | Q36: =IF(COUNT(E36:P36)=12,SUM(E36:P36),"")
A37: Dec-2026 acquisition cohort | E37: =0 | F37: =0 | G37: =0 | H37: =0 | I37: =0 | J37: =0 | K37: =0 | L37: =0 | ... O37: =0 | P37: =P20*Drivers!P14 | Q37: =IF(COUNT(E37:P37)=12,SUM(E37:P37),"")
A38: Total monthly recurring revenue | E38: =IF(COUNT(E25:E37)=13,SUM(E25:E37),"") | F38: =IF(COUNT(F25:F37)=13,SUM(F25:F37),"") | G38: =IF(COUNT(G25:G37)=13,SUM(G25:G37),"") | H38: =IF(COUNT(H25:H37)=13,SUM(H25:H37),"") | I38: =IF(COUNT(I25:I37)=13,SUM(I25:I37),"") | J38: =IF(COUNT(J25:J37)=13,SUM(J25:J37),"") | K38: =IF(COUNT(K25:K37)=13,SUM(K25:K37),"") | L38: =IF(COUNT(L25:L37)=13,SUM(L25:L37),"") | ... P38: =IF(COUNT(P25:P37)=13,SUM(P25:P37),"") | Q38: =IF(COUNT(E38:P38)=12,SUM(E38:P38),"")

Sheet Revenue
A1: NORTHSTAR CLOUD / REVENUE
A3: B | Initially growth-rate driven; after the follow-up, replace with cohort-linked revenue.
A5: USD, unless stated otherwise | B5: Oct-25 | C5: Nov-25 | D5: Dec-25 | E5: Jan-26 | F5: Feb-26 | G5: Mar-26 | H5: Apr-26 | I5: May-26 | J5: Jun-26 | K5: Jul-26 | L5: Aug-26 | M5: Sep-26 | N5: Oct-26 | O5: Nov-26 | P5: Dec-26 | Q5: FY26 / Exit | S5: MODEL NOTES
A6: Subscription revenue | B6: =Historical!B6 | C6: =Historical!C6 | D6: =Historical!D6 | E6: =Cohorts!E38 | F6: =Cohorts!F38 | G6: =Cohorts!G38 | H6: =Cohorts!H38 | I6: =Cohorts!I38 | J6: =Cohorts!J38 | K6: =Cohorts!K38 | L6: =Cohorts!L38 | ... P6: =Cohorts!P38 | Q6: =IF(COUNT(E6:P6)=12,SUM(E6:P6),"")
A7: Month-on-month revenue growth | C7: =C6/B6-1 | D7: =D6/C6-1 | E7: =E6/D6-1 | F7: =F6/E6-1 | G7: =G6/F6-1 | H7: =H6/G6-1 | I7: =I6/H6-1 | J7: =J6/I6-1 | ... P7: =P6/O6-1 | Q7: =IF(COUNT(E7:P7)=12,P7,"")
A8: Exit monthly recurring revenue | B8: =Historical!B6 | C8: =Historical!C6 | D8: =Historical!D6 | E8: =E6 | F8: =F6 | G8: =G6 | H8: =H6 | I8: =I6 | J8: =J6 | K8: =K6 | L8: =L6 | ... P8: =P6 | Q8: =IF(COUNT(E8:P8)=12,P8,"")
A9: Active customers | B9: =Historical!B24 | C9: =Historical!C24 | D9: =Historical!D24 | E9: =Cohorts!E21 | F9: =Cohorts!F21 | G9: =Cohorts!G21 | H9: =Cohorts!H21 | I9: =Cohorts!I21 | J9: =Cohorts!J21 | K9: =Cohorts!K21 | L9: =Cohorts!L21 | ... P9: =Cohorts!P21 | Q9: =IF(COUNT(E9:P9)=12,P9,"")
A10: Blended monthly ARPC | B10: =Historical!B25 | C10: =Historical!C25 | D10: =Historical!D25 | E10: =E6/E9 | F10: =F6/F9 | G10: =G6/G9 | H10: =H6/H9 | I10: =I6/I9 | J10: =J6/J9 | K10: =K6/K9 | L10: =L6/L9 | ... P10: =P6/P9 | Q10: =IF(COUNT(E10:P10)=12,P10,"")
S13: Initial method: monthly revenue = prior month revenue x (1 + Drivers row 6). Exit MRR equals revenue. Leave forecast rows 9-10 and all cohort targets blank.
S17: Revised method: subscription revenue and exit MRR link to Cohorts row 38; active customers link to Cohorts row 21; blended ARPC = revenue / active customers.
S21: Under either method, January growth compares with December historical revenue. All later growth compares with the immediately preceding month.

Sheet P&L
A1: NORTHSTAR CLOUD / P&L
A3: C | Complete operating expenses and earnings; revenue links are already installed.
A5: USD, unless stated otherwise | B5: Oct-25 | C5: Nov-25 | D5: Dec-25 | E5: Jan-26 | F5: Feb-26 | G5: Mar-26 | H5: Apr-26 | I5: May-26 | J5: Jun-26 | K5: Jul-26 | L5: Aug-26 | M5: Sep-26 | N5: Oct-26 | O5: Nov-26 | P5: Dec-26 | Q5: FY26 / Exit | S5: MODEL NOTES
A6: Subscription revenue | B6: =Historical!B6 | C6: =Historical!C6 | D6: =Historical!D6 | E6: =IF(ISNUMBER(Revenue!E6),Revenue!E6,"") | F6: =IF(ISNUMBER(Revenue!F6),Revenue!F6,"") | G6: =IF(ISNUMBER(Revenue!G6),Revenue!G6,"") | H6: =IF(ISNUMBER(Revenue!H6),Revenue!H6,"") | I6: =IF(ISNUMBER(Revenue!I6),Revenue!I6,"") | J6: =IF(ISNUMBER(Revenue!J6),Revenue!J6,"") | K6: =IF(ISNUMBER(Revenue!K6),Revenue!K6,"") | L6: =IF(ISNUMBER(Revenue!L6),Revenue!L6,"") | ... P6: =IF(ISNUMBER(Revenue!P6),Revenue!P6,"") | Q6: =IF(COUNT(E6:P6)=12,SUM(E6:P6),"")
A7: Hosting cost | B7: =Historical!B7 | C7: =Historical!C7 | D7: =Historical!D7 | E7: =E6*Drivers!E7 | F7: =F6*Drivers!F7 | G7: =G6*Drivers!G7 | H7: =H6*Drivers!H7 | I7: =I6*Drivers!I7 | J7: =J6*Drivers!J7 | K7: =K6*Drivers!K7 | L7: =L6*Drivers!L7 | ... P7: =P6*Drivers!P7 | Q7: =IF(COUNT(E7:P7)=12,SUM(E7:P7),"")
A8: Gross profit | B8: =Historical!B8 | C8: =Historical!C8 | D8: =Historical!D8 | E8: =E6-E7 | F8: =F6-F7 | G8: =G6-G7 | H8: =H6-H7 | I8: =I6-I7 | J8: =J6-J7 | K8: =K6-K7 | L8: =L6-L7 | ... P8: =P6-P7 | Q8: =IF(COUNT(E8:P8)=12,SUM(E8:P8),"")
A9: Payroll | B9: =Historical!B9 | C9: =Historical!C9 | D9: =Historical!D9 | E9: =D9*(1+Drivers!E18) | F9: =E9*(1+Drivers!F18) | G9: =F9*(1+Drivers!G18) | H9: =G9*(1+Drivers!H18) | I9: =H9*(1+Drivers!I18) | J9: =I9*(1+Drivers!J18) | K9: =J9*(1+Drivers!K18) | L9: =K9*(1+Drivers!L18) | ... P9: =O9*(1+Drivers!P18) | Q9: =IF(COUNT(E9:P9)=12,SUM(E9:P9),"")
A10: Sales & marketing | B10: =Historical!B10 | C10: =Historical!C10 | D10: =Historical!D10 | E10: =E6*Drivers!E19 | F10: =F6*Drivers!F19 | G10: =G6*Drivers!G19 | H10: =H6*Drivers!H19 | I10: =I6*Drivers!I19 | J10: =J6*Drivers!J19 | K10: =K6*Drivers!K19 | L10: =L6*Drivers!L19 | ... P10: =P6*Drivers!P19 | Q10: =IF(COUNT(E10:P10)=12,SUM(E10:P10),"")
A11: General & administrative | B11: =Historical!B11 | C11: =Historical!C11 | D11: =Historical!D11 | E11: =D11*(1+Drivers!E20) | F11: =E11*(1+Drivers!F20) | G11: =F11*(1+Drivers!G20) | H11: =G11*(1+Drivers!H20) | I11: =H11*(1+Drivers!I20) | J11: =I11*(1+Drivers!J20) | K11: =J11*(1+Drivers!K20) | L11: =K11*(1+Drivers!L20) | ... P11: =O11*(1+Drivers!P20) | Q11: =IF(COUNT(E11:P11)=12,SUM(E11:P11),"")
A12: EBITDA | B12: =Historical!B12 | C12: =Historical!C12 | D12: =Historical!D12 | E12: =E8-E9-E10-E11 | F12: =F8-F9-F10-F11 | G12: =G8-G9-G10-G11 | H12: =H8-H9-H10-H11 | I12: =I8-I9-I10-I11 | J12: =J8-J9-J10-J11 | K12: =K8-K9-K10-K11 | L12: =L8-L9-L10-L11 | ... P12: =P8-P9-P10-P11 | Q12: =IF(COUNT(E12:P12)=12,SUM(E12:P12),"")
A13: Depreciation | B13: =Historical!B13 | C13: =Historical!C13 | D13: =Historical!D13 | E13: =Drivers!E21 | F13: =Drivers!F21 | G13: =Drivers!G21 | H13: =Drivers!H21 | I13: =Drivers!I21 | J13: =Drivers!J21 | K13: =Drivers!K21 | L13: =Drivers!L21 | ... P13: =Drivers!P21 | Q13: =IF(COUNT(E13:P13)=12,SUM(E13:P13),"")
A14: EBIT | B14: =Historical!B14 | C14: =Historical!C14 | D14: =Historical!D14 | E14: =E12-E13 | F14: =F12-F13 | G14: =G12-G13 | H14: =H12-H13 | I14: =I12-I13 | J14: =J12-J13 | K14: =K12-K13 | L14: =L12-L13 | ... P14: =P12-P13 | Q14: =IF(COUNT(E14:P14)=12,SUM(E14:P14),"")
A15: Interest | B15: =Historical!B15 | C15: =Historical!C15 | D15: =Historical!D15 | E15: ='Cash Flow'!E13*Drivers!E24/12 | F15: ='Cash Flow'!F13*Drivers!F24/12 | G15: ='Cash Flow'!G13*Drivers!G24/12 | H15: ='Cash Flow'!H13*Drivers!H24/12 | I15: ='Cash Flow'!I13*Drivers!I24/12 | J15: ='Cash Flow'!J13*Drivers!J24/12 | K15: ='Cash Flow'!K13*Drivers!K24/12 | L15: ='Cash Flow'!L13*Drivers!L24/12 | ... P15: ='Cash Flow'!P13*Drivers!P24/12 | Q15: =IF(COUNT(E15:P15)=12,SUM(E15:P15),"")
A16: Cash taxes | B16: =Historical!B16 | C16: =Historical!C16 | D16: =Historical!D16 | E16: =MAX(E14-E15,0)*Drivers!E8 | F16: =MAX(F14-F15,0)*Drivers!F8 | G16: =MAX(G14-G15,0)*Drivers!G8 | H16: =MAX(H14-H15,0)*Drivers!H8 | I16: =MAX(I14-I15,0)*Drivers!I8 | J16: =MAX(J14-J15,0)*Drivers!J8 | K16: =MAX(K14-K15,0)*Drivers!K8 | L16: =MAX(L14-L15,0)*Drivers!L8 | ... P16: =MAX(P14-P15,0)*Drivers!P8 | Q16: =IF(COUNT(E16:P16)=12,SUM(E16:P16),"")
A17: Net income | B17: =Historical!B17 | C17: =Historical!C17 | D17: =Historical!D17 | E17: =E14-E15-E16 | F17: =F14-F15-F16 | G17: =G14-G15-G16 | H17: =H14-H15-H16 | I17: =I14-I15-I16 | J17: =J14-J15-J16 | K17: =K14-K15-K16 | L17: =L14-L15-L16 | ... P17: =P14-P15-P16 | Q17: =IF(COUNT(E17:P17)=12,SUM(E17:P17),"")
S20: Expenses are positive values. Gross profit = revenue - hosting. EBITDA = gross profit - payroll - S&M - G&A. EBIT = EBITDA - depreciation.
S23: Interest uses OPENING revolver debt x annual interest / 12. Taxes = MAX(EBIT - interest, 0) x tax rate. Net income = EBIT - interest - taxes.

Sheet Working Capital
A1: NORTHSTAR CLOUD / WORKING CAPITAL
A3: A | Forecast receivables and payables using actual calendar days, then compute cash movements.
A5: USD, unless stated otherwise | B5: Oct-25 | C5: Nov-25 | D5: Dec-25 | E5: Jan-26 | F5: Feb-26 | G5: Mar-26 | H5: Apr-26 | I5: May-26 | J5: Jun-26 | K5: Jul-26 | L5: Aug-26 | M5: Sep-26 | N5: Oct-26 | O5: Nov-26 | P5: Dec-26 | Q5: FY26 / Exit | S5: MODEL NOTES
A6: Accounts receivable | B6: =Historical!B20 | C6: =Historical!C20 | D6: =Historical!D20 | E6: =Revenue!E6/Drivers!E25*Drivers!E16 | F6: =Revenue!F6/Drivers!F25*Drivers!F16 | G6: =Revenue!G6/Drivers!G25*Drivers!G16 | H6: =Revenue!H6/Drivers!H25*Drivers!H16 | I6: =Revenue!I6/Drivers!I25*Drivers!I16 | J6: =Revenue!J6/Drivers!J25*Drivers!J16 | K6: =Revenue!K6/Drivers!K25*Drivers!K16 | L6: =Revenue!L6/Drivers!L25*Drivers!L16 | ... P6: =Revenue!P6/Drivers!P25*Drivers!P16 | Q6: =IF(COUNT(E6:P6)=12,P6,"")
A7: Accounts payable | B7: =Historical!B21 | C7: =Historical!C21 | D7: =Historical!D21 | E7: ='P&L'!E7/Drivers!E25*Drivers!E17 | F7: ='P&L'!F7/Drivers!F25*Drivers!F17 | G7: ='P&L'!G7/Drivers!G25*Drivers!G17 | H7: ='P&L'!H7/Drivers!H25*Drivers!H17 | I7: ='P&L'!I7/Drivers!I25*Drivers!I17 | J7: ='P&L'!J7/Drivers!J25*Drivers!J17 | K7: ='P&L'!K7/Drivers!K25*Drivers!K17 | L7: ='P&L'!L7/Drivers!L25*Drivers!L17 | ... P7: ='P&L'!P7/Drivers!P25*Drivers!P17 | Q7: =IF(COUNT(E7:P7)=12,P7,"")
A8: Net operating working capital | B8: =B6-B7 | C8: =C6-C7 | D8: =D6-D7 | E8: =E6-E7 | F8: =F6-F7 | G8: =G6-G7 | H8: =H6-H7 | I8: =I6-I7 | ... P8: =P6-P7 | Q8: =IF(COUNT(E8:P8)=12,P8,"")
A10: Increase / (decrease) in AR | E10: =E6-D6 | F10: =F6-E6 | G10: =G6-F6 | H10: =H6-G6 | I10: =I6-H6 | J10: =J6-I6 | K10: =K6-J6 | L10: =L6-K6 | ... P10: =P6-O6 | Q10: =IF(COUNT(E10:P10)=12,SUM(E10:P10),"")
A11: Increase / (decrease) in AP | E11: =E7-D7 | F11: =F7-E7 | G11: =G7-F7 | H11: =H7-G7 | I11: =I7-H7 | J11: =J7-I7 | K11: =K7-J7 | L11: =L7-K7 | ... P11: =P7-O7 | Q11: =IF(COUNT(E11:P11)=12,SUM(E11:P11),"")
A12: Working-capital cash impact | E12: =-E10+E11 | F12: =-F10+F11 | G12: =-G10+G11 | H12: =-H10+H11 | I12: =-I10+I11 | J12: =-J10+J11 | K12: =-K10+K11 | L12: =-L10+L11 | ... P12: =-P10+P11 | Q12: =IF(COUNT(E12:P12)=12,SUM(E12:P12),"")
S15: AR = current-month revenue / days in month x DSO. AP = current-month hosting cost / days in month x DPO. No inventory, accrued payroll or other operating balances.
S19: Monthly movements = current balance - prior balance; January uses December actuals. Cash impact = -change in AR + change in AP.

Sheet Cash Flow
A1: NORTHSTAR CLOUD / CASH FLOW
A3: C | Close the cash and revolver schedules without circular references.
A5: USD, unless stated otherwise | B5: Oct-25 | C5: Nov-25 | D5: Dec-25 | E5: Jan-26 | F5: Feb-26 | G5: Mar-26 | H5: Apr-26 | I5: May-26 | J5: Jun-26 | K5: Jul-26 | L5: Aug-26 | M5: Sep-26 | N5: Oct-26 | O5: Nov-26 | P5: Dec-26 | Q5: FY26 / Exit | S5: MODEL NOTES
A6: Opening cash | E6: =IF(ISNUMBER(Historical!D22),Historical!D22,"") | F6: =IF(ISNUMBER(E17),E17,"") | G6: =IF(ISNUMBER(F17),F17,"") | H6: =IF(ISNUMBER(G17),G17,"") | I6: =IF(ISNUMBER(H17),H17,"") | J6: =IF(ISNUMBER(I17),I17,"") | K6: =IF(ISNUMBER(J17),J17,"") | L6: =IF(ISNUMBER(K17),K17,"") | M6: =IF(ISNUMBER(L17),L17,"") | ... P6: =IF(ISNUMBER(O17),O17,"") | Q6: =IF(ISNUMBER(E6),E6,"")
A7: Net income | E7: =IF(ISNUMBER('P&L'!E17),'P&L'!E17,"") | F7: =IF(ISNUMBER('P&L'!F17),'P&L'!F17,"") | G7: =IF(ISNUMBER('P&L'!G17),'P&L'!G17,"") | H7: =IF(ISNUMBER('P&L'!H17),'P&L'!H17,"") | I7: =IF(ISNUMBER('P&L'!I17),'P&L'!I17,"") | J7: =IF(ISNUMBER('P&L'!J17),'P&L'!J17,"") | K7: =IF(ISNUMBER('P&L'!K17),'P&L'!K17,"") | L7: =IF(ISNUMBER('P&L'!L17),'P&L'!L17,"") | ... P7: =IF(ISNUMBER('P&L'!P17),'P&L'!P17,"") | Q7: =IF(COUNT(E7:P7)=12,SUM(E7:P7),"")
A8: Depreciation add-back | E8: =IF(ISNUMBER('P&L'!E13),'P&L'!E13,"") | F8: =IF(ISNUMBER('P&L'!F13),'P&L'!F13,"") | G8: =IF(ISNUMBER('P&L'!G13),'P&L'!G13,"") | H8: =IF(ISNUMBER('P&L'!H13),'P&L'!H13,"") | I8: =IF(ISNUMBER('P&L'!I13),'P&L'!I13,"") | J8: =IF(ISNUMBER('P&L'!J13),'P&L'!J13,"") | K8: =IF(ISNUMBER('P&L'!K13),'P&L'!K13,"") | L8: =IF(ISNUMBER('P&L'!L13),'P&L'!L13,"") | ... P8: =IF(ISNUMBER('P&L'!P13),'P&L'!P13,"") | Q8: =IF(COUNT(E8:P8)=12,SUM(E8:P8),"")
A9: Working-capital cash impact | E9: =IF(ISNUMBER('Working Capital'!E12),'Working Capital'!E12,"") | F9: =IF(ISNUMBER('Working Capital'!F12),'Working Capital'!F12,"") | G9: =IF(ISNUMBER('Working Capital'!G12),'Working Capital'!G12,"") | H9: =IF(ISNUMBER('Working Capital'!H12),'Working Capital'!H12,"") | I9: =IF(ISNUMBER('Working Capital'!I12),'Working Capital'!I12,"") | J9: =IF(ISNUMBER('Working Capital'!J12),'Working Capital'!J12,"") | K9: =IF(ISNUMBER('Working Capital'!K12),'Working Capital'!K12,"") | L9: =IF(ISNUMBER('Working Capital'!L12),'Working Capital'!L12,"") | ... P9: =IF(ISNUMBER('Working Capital'!P12),'Working Capital'!P12,"") | Q9: =IF(COUNT(E9:P9)=12,SUM(E9:P9),"")
A10: Cash flow from operations | E10: =E7+E8+E9 | F10: =F7+F8+F9 | G10: =G7+G8+G9 | H10: =H7+H8+H9 | I10: =I7+I8+I9 | J10: =J7+J8+J9 | K10: =K7+K8+K9 | L10: =L7+L8+L9 | ... P10: =P7+P8+P9 | Q10: =IF(COUNT(E10:P10)=12,SUM(E10:P10),"")
A11: Capital expenditure (outflow) | E11: =IF(ISNUMBER(Drivers!E22),Drivers!E22,"") | F11: =IF(ISNUMBER(Drivers!F22),Drivers!F22,"") | G11: =IF(ISNUMBER(Drivers!G22),Drivers!G22,"") | H11: =IF(ISNUMBER(Drivers!H22),Drivers!H22,"") | I11: =IF(ISNUMBER(Drivers!I22),Drivers!I22,"") | J11: =IF(ISNUMBER(Drivers!J22),Drivers!J22,"") | K11: =IF(ISNUMBER(Drivers!K22),Drivers!K22,"") | L11: =IF(ISNUMBER(Drivers!L22),Drivers!L22,"") | ... P11: =IF(ISNUMBER(Drivers!P22),Drivers!P22,"") | Q11: =IF(COUNT(E11:P11)=12,SUM(E11:P11),"")
A12: Pre-financing closing cash | E12: =E6+E10-E11 | F12: =F6+F10-F11 | G12: =G6+G10-G11 | H12: =H6+H10-H11 | I12: =I6+I10-I11 | J12: =J6+J10-J11 | K12: =K6+K10-K11 | L12: =L6+L10-L11 | ... P12: =P6+P10-P11 | Q12: =IF(COUNT(E12:P12)=12,SUM(E12:P12),"")
A13: Opening revolver balance | E13: =IF(ISNUMBER(Historical!D23),Historical!D23,"") | F13: =IF(ISNUMBER(E18),E18,"") | G13: =IF(ISNUMBER(F18),F18,"") | H13: =IF(ISNUMBER(G18),G18,"") | I13: =IF(ISNUMBER(H18),H18,"") | J13: =IF(ISNUMBER(I18),I18,"") | K13: =IF(ISNUMBER(J18),J18,"") | L13: =IF(ISNUMBER(K18),K18,"") | M13: =IF(ISNUMBER(L18),L18,"") | ... P13: =IF(ISNUMBER(O18),O18,"") | Q13: =IF(ISNUMBER(E13),E13,"")
A14: Revolver draw | E14: =MAX(Drivers!E23-E12,0) | F14: =MAX(Drivers!F23-F12,0) | G14: =MAX(Drivers!G23-G12,0) | H14: =MAX(Drivers!H23-H12,0) | I14: =MAX(Drivers!I23-I12,0) | J14: =MAX(Drivers!J23-J12,0) | K14: =MAX(Drivers!K23-K12,0) | L14: =MAX(Drivers!L23-L12,0) | ... P14: =MAX(Drivers!P23-P12,0) | Q14: =IF(COUNT(E14:P14)=12,SUM(E14:P14),"")
A15: Revolver repayment | E15: =MIN(E13,MAX(E12-Drivers!E23,0)) | F15: =MIN(F13,MAX(F12-Drivers!F23,0)) | G15: =MIN(G13,MAX(G12-Drivers!G23,0)) | H15: =MIN(H13,MAX(H12-Drivers!H23,0)) | I15: =MIN(I13,MAX(I12-Drivers!I23,0)) | J15: =MIN(J13,MAX(J12-Drivers!J23,0)) | K15: =MIN(K13,MAX(K12-Drivers!K23,0)) | L15: =MIN(L13,MAX(L12-Drivers!L23,0)) | ... P15: =MIN(P13,MAX(P12-Drivers!P23,0)) | Q15: =IF(COUNT(E15:P15)=12,SUM(E15:P15),"")
A16: Net financing cash flow | E16: =E14-E15 | F16: =F14-F15 | G16: =G14-G15 | H16: =H14-H15 | I16: =I14-I15 | J16: =J14-J15 | K16: =K14-K15 | L16: =L14-L15 | ... P16: =P14-P15 | Q16: =IF(COUNT(E16:P16)=12,SUM(E16:P16),"")
A17: Closing cash | E17: =E12+E16 | F17: =F12+F16 | G17: =G12+G16 | H17: =H12+H16 | I17: =I12+I16 | J17: =J12+J16 | K17: =K12+K16 | L17: =L12+L16 | ... P17: =P12+P16 | Q17: =IF(COUNT(E17:P17)=12,P17,"")
A18: Closing revolver balance | E18: =E13+E16 | F18: =F13+F16 | G18: =G13+G16 | H18: =H13+H16 | I18: =I13+I16 | J18: =J13+J16 | K18: =K13+K16 | L18: =L13+L16 | ... P18: =P13+P16 | Q18: =IF(COUNT(E18:P18)=12,P18,"")
S21: CFO = net income + depreciation + working-capital cash impact. Capex and repayments are POSITIVE outflows. Pre-financing closing cash = opening cash + CFO - capex.
S24: Draw = MAX(minimum cash - pre-financing cash, 0). Repay = MIN(opening debt, MAX(pre-financing cash - minimum cash, 0)). Revolver is uncapped; never draw and repay together.
S27: Net financing = draw - repayment. Closing cash = pre-financing cash + net financing. Closing debt = opening debt + net financing. No dividends, equity or other investing flows.

Sheet Checks
A1: NORTHSTAR CLOUD / CHECKS
A3: C | Fill numeric residuals. Zero means pass; evaluate only after completing the applicable forecast.
A5: USD, unless stated otherwise | B5: Oct-25 | C5: Nov-25 | D5: Dec-25 | E5: Jan-26 | F5: Feb-26 | G5: Mar-26 | H5: Apr-26 | I5: May-26 | J5: Jun-26 | K5: Jul-26 | L5: Aug-26 | M5: Sep-26 | N5: Oct-26 | O5: Nov-26 | P5: Dec-26 | Q5: FY26 / Exit | S5: MODEL NOTES
A6: Revenue-to-P&L residual | E6: ='P&L'!E6-Revenue!E6 | F6: ='P&L'!F6-Revenue!F6 | G6: ='P&L'!G6-Revenue!G6 | H6: ='P&L'!H6-Revenue!H6 | I6: ='P&L'!I6-Revenue!I6 | J6: ='P&L'!J6-Revenue!J6 | K6: ='P&L'!K6-Revenue!K6 | L6: ='P&L'!L6-Revenue!L6 | ... P6: ='P&L'!P6-Revenue!P6 | Q6: =IF(COUNT(E6:P6)=12,MAX(ABS(MIN(E6:P6)),ABS(MAX(E6:P6))),"")
A7: Receivables days residual | E7: ='Working Capital'!E6/Revenue!E6*Drivers!E25-Drivers!E16 | F7: ='Working Capital'!F6/Revenue!F6*Drivers!F25-Drivers!F16 | G7: ='Working Capital'!G6/Revenue!G6*Drivers!G25-Drivers!G16 | H7: ='Working Capital'!H6/Revenue!H6*Drivers!H25-Drivers!H16 | I7: ='Working Capital'!I6/Revenue!I6*Drivers!I25-Drivers!I16 | J7: ='Working Capital'!J6/Revenue!J6*Drivers!J25-Drivers!J16 | K7: ='Working Capital'!K6/Revenue!K6*Drivers!K25-Drivers!K16 | L7: ='Working Capital'!L6/Revenue!L6*Drivers!L25-Drivers!L16 | ... P7: ='Working Capital'!P6/Revenue!P6*Drivers!P25-Drivers!P16 | Q7: =IF(COUNT(E7:P7)=12,MAX(ABS(MIN(E7:P7)),ABS(MAX(E7:P7))),"")
A8: Payables days residual | E8: ='Working Capital'!E7/'P&L'!E7*Drivers!E25-Drivers!E17 | F8: ='Working Capital'!F7/'P&L'!F7*Drivers!F25-Drivers!F17 | G8: ='Working Capital'!G7/'P&L'!G7*Drivers!G25-Drivers!G17 | H8: ='Working Capital'!H7/'P&L'!H7*Drivers!H25-Drivers!H17 | I8: ='Working Capital'!I7/'P&L'!I7*Drivers!I25-Drivers!I17 | J8: ='Working Capital'!J7/'P&L'!J7*Drivers!J25-Drivers!J17 | K8: ='Working Capital'!K7/'P&L'!K7*Drivers!K25-Drivers!K17 | L8: ='Working Capital'!L7/'P&L'!L7*Drivers!L25-Drivers!L17 | ... P8: ='Working Capital'!P7/'P&L'!P7*Drivers!P25-Drivers!P17 | Q8: =IF(COUNT(E8:P8)=12,MAX(ABS(MIN(E8:P8)),ABS(MAX(E8:P8))),"")
A9: Net income residual | E9: ='P&L'!E17-('P&L'!E14-'P&L'!E15-'P&L'!E16) | F9: ='P&L'!F17-('P&L'!F14-'P&L'!F15-'P&L'!F16) | G9: ='P&L'!G17-('P&L'!G14-'P&L'!G15-'P&L'!G16) | H9: ='P&L'!H17-('P&L'!H14-'P&L'!H15-'P&L'!H16) | I9: ='P&L'!I17-('P&L'!I14-'P&L'!I15-'P&L'!I16) | J9: ='P&L'!J17-('P&L'!J14-'P&L'!J15-'P&L'!J16) | K9: ='P&L'!K17-('P&L'!K14-'P&L'!K15-'P&L'!K16) | L9: ='P&L'!L17-('P&L'!L14-'P&L'!L15-'P&L'!L16) | ... P9: ='P&L'!P17-('P&L'!P14-'P&L'!P15-'P&L'!P16) | Q9: =IF(COUNT(E9:P9)=12,MAX(ABS(MIN(E9:P9)),ABS(MAX(E9:P9))),"")
A10: Cash roll-forward residual | E10: ='Cash Flow'!E17-('Cash Flow'!E6+'Cash Flow'!E10-'Cash Flow'!E11+'Cash Flow'!E14-'Cash Flow'!E15) | F10: ='Cash Flow'!F17-('Cash Flow'!F6+'Cash Flow'!F10-'Cash Flow'!F11+'Cash Flow'!F14-'Cash Flow'!F15) | G10: ='Cash Flow'!G17-('Cash Flow'!G6+'Cash Flow'!G10-'Cash Flow'!G11+'Cash Flow'!G14-'Cash Flow'!G15) | H10: ='Cash Flow'!H17-('Cash Flow'!H6+'Cash Flow'!H10-'Cash Flow'!H11+'Cash Flow'!H14-'Cash Flow'!H15) | I10: ='Cash Flow'!I17-('Cash Flow'!I6+'Cash Flow'!I10-'Cash Flow'!I11+'Cash Flow'!I14-'Cash Flow'!I15) | J10: ='Cash Flow'!J17-('Cash Flow'!J6+'Cash Flow'!J10-'Cash Flow'!J11+'Cash Flow'!J14-'Cash Flow'!J15) | K10: ='Cash Flow'!K17-('Cash Flow'!K6+'Cash Flow'!K10-'Cash Flow'!K11+'Cash Flow'!K14-'Cash Flow'!K15) | L10: ='Cash Flow'!L17-('Cash Flow'!L6+'Cash Flow'!L10-'Cash Flow'!L11+'Cash Flow'!L14-'Cash Flow'!L15) | ... P10: ='Cash Flow'!P17-('Cash Flow'!P6+'Cash Flow'!P10-'Cash Flow'!P11+'Cash Flow'!P14-'Cash Flow'!P15) | Q10: =IF(COUNT(E10:P10)=12,MAX(ABS(MIN(E10:P10)),ABS(MAX(E10:P10))),"")
A11: Debt roll-forward residual | E11: ='Cash Flow'!E18-('Cash Flow'!E13+'Cash Flow'!E14-'Cash Flow'!E15) | F11: ='Cash Flow'!F18-('Cash Flow'!F13+'Cash Flow'!F14-'Cash Flow'!F15) | G11: ='Cash Flow'!G18-('Cash Flow'!G13+'Cash Flow'!G14-'Cash Flow'!G15) | H11: ='Cash Flow'!H18-('Cash Flow'!H13+'Cash Flow'!H14-'Cash Flow'!H15) | I11: ='Cash Flow'!I18-('Cash Flow'!I13+'Cash Flow'!I14-'Cash Flow'!I15) | J11: ='Cash Flow'!J18-('Cash Flow'!J13+'Cash Flow'!J14-'Cash Flow'!J15) | K11: ='Cash Flow'!K18-('Cash Flow'!K13+'Cash Flow'!K14-'Cash Flow'!K15) | L11: ='Cash Flow'!L18-('Cash Flow'!L13+'Cash Flow'!L14-'Cash Flow'!L15) | ... P11: ='Cash Flow'!P18-('Cash Flow'!P13+'Cash Flow'!P14-'Cash Flow'!P15) | Q11: =IF(COUNT(E11:P11)=12,MAX(ABS(MIN(E11:P11)),ABS(MAX(E11:P11))),"")
A12: Cash minimum shortfall | E12: =MAX(Drivers!E23-'Cash Flow'!E17,0) | F12: =MAX(Drivers!F23-'Cash Flow'!F17,0) | G12: =MAX(Drivers!G23-'Cash Flow'!G17,0) | H12: =MAX(Drivers!H23-'Cash Flow'!H17,0) | I12: =MAX(Drivers!I23-'Cash Flow'!I17,0) | J12: =MAX(Drivers!J23-'Cash Flow'!J17,0) | K12: =MAX(Drivers!K23-'Cash Flow'!K17,0) | L12: =MAX(Drivers!L23-'Cash Flow'!L17,0) | ... P12: =MAX(Drivers!P23-'Cash Flow'!P17,0) | Q12: =IF(COUNT(E12:P12)=12,MAX(ABS(MIN(E12:P12)),ABS(MAX(E12:P12))),"")
A13: Simultaneous draw / repay | E13: =MIN('Cash Flow'!E14,'Cash Flow'!E15) | F13: =MIN('Cash Flow'!F14,'Cash Flow'!F15) | G13: =MIN('Cash Flow'!G14,'Cash Flow'!G15) | H13: =MIN('Cash Flow'!H14,'Cash Flow'!H15) | I13: =MIN('Cash Flow'!I14,'Cash Flow'!I15) | J13: =MIN('Cash Flow'!J14,'Cash Flow'!J15) | K13: =MIN('Cash Flow'!K14,'Cash Flow'!K15) | L13: =MIN('Cash Flow'!L14,'Cash Flow'!L15) | ... P13: =MIN('Cash Flow'!P14,'Cash Flow'!P15) | Q13: =IF(COUNT(E13:P13)=12,MAX(ABS(MIN(E13:P13)),ABS(MAX(E13:P13))),"")
A14: Cohort revenue tie-out | E14: =Revenue!E6-Cohorts!E38 | F14: =Revenue!F6-Cohorts!F38 | G14: =Revenue!G6-Cohorts!G38 | H14: =Revenue!H6-Cohorts!H38 | I14: =Revenue!I6-Cohorts!I38 | J14: =Revenue!J6-Cohorts!J38 | K14: =Revenue!K6-Cohorts!K38 | L14: =Revenue!L6-Cohorts!L38 | ... P14: =Revenue!P6-Cohorts!P38 | Q14: =IF(COUNT(E14:P14)=12,MAX(ABS(MIN(E14:P14)),ABS(MAX(E14:P14))),"")
A15: Cohort customer tie-out | E15: =Revenue!E9-Cohorts!E21 | F15: =Revenue!F9-Cohorts!F21 | G15: =Revenue!G9-Cohorts!G21 | H15: =Revenue!H9-Cohorts!H21 | I15: =Revenue!I9-Cohorts!I21 | J15: =Revenue!J9-Cohorts!J21 | K15: =Revenue!K9-Cohorts!K21 | L15: =Revenue!L9-Cohorts!L21 | ... P15: =Revenue!P9-Cohorts!P21 | Q15: =IF(COUNT(E15:P15)=12,MAX(ABS(MIN(E15:P15)),ABS(MAX(E15:P15))),"")
S18: Use formula-driven residuals, never hardcoded zeros (except cohort tie-outs before the follow-up). Tolerance: absolute residual <= $0.005 or 0.005 customers.
S21: The explicit task instructions define each residual. FY26 / Exit shows the maximum absolute monthly residual, not the sum.
S24: After the change, rows 14-15 must tie the revenue schedule to the cohort schedule. Existing conditional formatting must remain intact.
